{
  "absorb_workflow": {
    "source": "sz absorb draft plus deterministic protocol adapter",
    "status": "materialized_with_functional_hardening"
  },
  "behaviors": [
    "delete verification outcome files created by draft checks",
    "remove matching verifier entries from external output logs",
    "remove matching intercepted email signal records idempotently"
  ],
  "capability": "ce.email.verification.rollback",
  "event_type": "ce.email.verification.rollback.snapshot",
  "interfaces": [
    "bus",
    "memory",
    "discovery",
    "storage"
  ],
  "module_id": "rollback-email-verification-ce",
  "public_purpose": "Removes generic email verification artifacts from shared System Zero storage.",
  "reconstruction": "Protocol-native behavior was re-derived from the source candidate and hardened into an anonymized System Zero module.",
  "source_kind": "script",
  "source_label": "core/system/scripts/rollback-email-verification.py",
  "source_metrics": {
    "extensions": {
      ".py": 1
    },
    "file_count": 1,
    "function_count": 1,
    "line_count": 85
  },
  "source_summary": "rollback-email-verification.py \u2014 remove email draft verification artifacts."
}
