{
  "absorb_workflow": {
    "source": "sz absorb draft plus deterministic protocol adapter",
    "status": "materialized_with_functional_hardening"
  },
  "behaviors": [
    "read shared content policy and posting markdown files",
    "verify only approved content is eligible for automated posting",
    "emit precise policy drift findings without touching account data"
  ],
  "capability": "ce.content.autopost.policy",
  "event_type": "ce.content.autopost.policy.snapshot",
  "interfaces": [
    "bus",
    "memory",
    "discovery",
    "storage"
  ],
  "module_id": "check-linkedin-autopost-policy-ce",
  "public_purpose": "Checks generic content auto-post policy files for stale eligibility and cadence language.",
  "reconstruction": "Protocol-native behavior was re-derived from the source candidate and hardened into an anonymized System Zero module.",
  "source_kind": "script",
  "source_label": "core/system/scripts/check_linkedin_autopost_policy.py",
  "source_metrics": {
    "extensions": {
      ".py": 1
    },
    "file_count": 1,
    "function_count": 2,
    "line_count": 85
  },
  "source_summary": "Detect drift in LinkedIn auto-post eligibility and cadence copy."
}
